{"filename":"invoice-northstar-2026-04-15.pdf","drive_file_id":"1zaCugp4VR5UCImuxRsOgZWEvSJagHX4x","drive_view_url":"https://drive.google.com/file/d/1zaCugp4VR5UCImuxRsOgZWEvSJagHX4x/view?usp=drivesdk","document_type":"Invoice","classification_confidence":"High","needs_human_review":false,"review_reason":null,"overall_score":95,"fields":{"vendor":{"value":"Northstar Consulting LLC","confidence":"High","evidence":"NORTHSTAR CONSULTING LLC 742 Evergreen Terrace Austin, TX 78701"},"invoice_number":{"value":"INV-2026-0415","confidence":"High","evidence":"Invoice #: INV-2026-0415"},"issue_date":{"value":"2026-04-15","confidence":"High","evidence":"Issue Date: April 15, 2026"},"due_date":{"value":"2026-05-15","confidence":"High","evidence":"Due Date: May 15, 2026"},"line_items":{"value":[{"description":"Strategic advisory, Q2 2026","qty":1,"rate":8500.00,"amount":8500.00},{"description":"EHR integration workshop (2 days)","qty":2,"rate":3200.00,"amount":6400.00},{"description":"Follow-up consultation","qty":4,"rate":450.00,"amount":1800.00}],"confidence":"High","evidence":"Strategic advisory, Q2 2026 1 $8,500.00 $8,500.00 EHR integration workshop (2 days) 2 $3,200.00 $6,400.00 Follow-up consultation 4 $450.00 $1,800.00"},"total_amount":{"value":18077.75,"confidence":"High","evidence":"TOTAL DUE: $18,077.75"}}}
